catx/__init__.py
catx/catx.py
catx/network_module.py
catx/tree.py
catx/type_defs.py
catx-0.2.1.dist-info/LICENSE
catx-0.2.1.dist-info/METADATA
catx-0.2.1.dist-info/WHEEL
catx-0.2.1.dist-info/entry_points.txt
catx-0.2.1.dist-info/top_level.txt
catx-0.2.1.dist-info/RECORD
